passwordgenerator/__init__.py
passwordgenerator/password-generator.py
projetpasswordgenerator-0.0.0.dist-info/METADATA
projetpasswordgenerator-0.0.0.dist-info/WHEEL
projetpasswordgenerator-0.0.0.dist-info/top_level.txt
projetpasswordgenerator-0.0.0.dist-info/RECORD
