Metadata-Version: 2.1
Name: projetpasswordgenerator
Version: 0.0.0
Summary: Generate random password
Author: Steeve EMMANUEL & Wisner AURELUS
Requires-Python: >=3.10
